{
  "chapter": "001",
  "book": "hanshu",
  "extractedAt": "2025-12-24T07:15:58.665Z",
  "translations": [
    {
      "id": "s0296",
      "type": "paragraph",
      "chinese": "吏卒皆山東之人，日夜企而望歸，及其鋒而用之，可以有大功。",
      "english": "The officials and soldiers are all men from east of the mountains. Day and night they crane their necks longing to return home. If you take advantage of their keen edge and use them now, you can achieve great merit.",
      "context": {}
    },
    {
      "id": "s0297",
      "type": "paragraph",
      "chinese": "天下已定，民皆自寧，不可復用。",
      "english": "When the world is pacified, the people will all be at peace. They cannot be used again.",
      "context": {}
    },
    {
      "id": "s0298",
      "type": "paragraph",
      "chinese": "不如決策東向。」",
      "english": "It would be better to decide now and advance east.\"",
      "context": {}
    },
    {
      "id": "s0299",
      "type": "paragraph",
      "chinese": "因陳羽可圖三秦易 并之計。",
      "english": "He then laid out the plan for how Xiang Yu could be plotted against and the three Qins easily united.",
      "context": {}
    },
    {
      "id": "s0300",
      "type": "paragraph",
      "chinese": "漢王大說，遂聽信策，部署諸將。",
      "english": "King Han was greatly pleased and followed Xin's strategy, deploying the various generals.",
      "context": {}
    }
  ]
}