{
  "meta": {
    "book": "beiqishu",
    "bookInfo": {
      "name": "Book of Northern Qi",
      "chinese": "北齊書",
      "pinyin": "Běi Qíshū",
      "dynasty": "Northern Qi"
    },
    "chapter": "013",
    "url": "https://chinesenotes.com/beiqishu/beiqishu013.html",
    "title": {
      "zh": "卷十三 列傳第五 趙郡王琛 子叡 清河王岳 子勱",
      "en": "Volume 13 Biographies 5: Gao Chen; Gao Rui (Northern Qi); Gao Yue (Northern Qi); Gao Mai",
      "raw": "卷十三 列傳第五 趙郡王琛 子叡 清河王岳 子勱 Volume 13 Biographies 5: Gao Chen; Gao Rui (Northern Qi); Gao Yue (Northern Qi); Gao Mai"
    },
    "sentenceCount": 239,
    "translatedCount": 0,
    "glossarySize": 39736,
    "scrapedAt": "2026-04-25T21:53:16.029Z",
    "translators": [],
    "citation": null
  },
  "content": [
    {
      "type": "paragraph",
      "sentences": [
        {
          "id": "s0001",
          "zh": "趙郡王琛 子叡 清河王岳 子勱",
          "translations": [
            {
              "lang": "en",
              "literal": "",
              "idiomatic": "",
              "translator": ""
            }
          ]
        }
      ],
      "translations": [
        {
          "lang": "en",
          "literal": "",
          "idiomatic": "",
          "translator": ""
        }
      ]
    },
    {
      "type": "paragraph",
      "sentences": [
        {
          "id": "s0002",
          "zh": "趙郡王琛，字永寶，高祖之弟也。",
          "translations": [
            {
              "lang": "en",
              "literal": "",
              "idiomatic": "",
              "translator": ""
            }
          ]
        },
        {
          "id": "s0003",
          "zh": "少時便弓馬，有志氣。",
          "translations": [
            {
              "lang": "en",
              "literal": "",
              "idiomatic": "",
              "translator": ""
            }
          ]
        },
        {
          "id": "s0004",
          "zh": "高祖既匡天下，中興初，授散騎常侍、鎮西將軍、金紫光祿大夫。",
          "translations": [
            {
              "lang": "en",
              "literal": "",
              "idiomatic": "",
              "translator": ""
            }
          ]
        },
        {
          "id": "s0005",
          "zh": "既居禁衛，恭勤慎密，率先左右。",
          "translations": [
            {
              "lang": "en",
              "literal": "",
              "idiomatic": "",
              "translator": ""
            }
          ]
        },
        {
          "id": "s0006",
          "zh": "太昌初，除車騎大將軍、左光祿大夫，封南趙郡公，食邑五千戶。",
          "translations": [
            {
              "lang": "en",
              "literal": "",
              "idiomatic": "",
              "translator": ""
            }
          ]
        },
        {
          "id": "s0007",
          "zh": "尋拜驃騎大將軍、特進、開府儀同三司、散騎常侍。",
          "translations": [
            {
              "lang": "en",
              "literal": "",
              "idiomatic": "",
              "translator": ""
            }
          ]
        },
        {
          "id": "s0008",
          "zh": "永熙二年，除使持節、都督定州刺史、六州大都督。",
          "translations": [
            {
              "lang": "en",
              "literal": "",
              "idiomatic": "",
              "translator": ""
            }
          ]
        },
        {
          "id": "s0009",
          "zh": "琛推誠撫納，拔用人士，甚有聲譽。",
          "translations": [
            {
              "lang": "en",
              "literal": "",
              "idiomatic": "",
              "translator": ""
            }
          ]
        },
        {
          "id": "s0010",
          "zh": "及斛斯椿等釁結。",
          "translations": [
            {
              "lang": "en",
              "literal": "",
              "idiomatic": "",
              "translator": ""
            }
          ]
        },
        {
          "id": "s0011",
          "zh": "高祖將謀內討，以晉陽根本，召琛留掌後事，以為幷、肆、汾大行臺僕射，領六州九酋長大都督，其相府政事琛悉決之。",
          "translations": [
            {
              "lang": "en",
              "literal": "",
              "idiomatic": "",
              "translator": ""
            }
          ]
        },
        {
          "id": "s0012",
          "zh": "天平中，除御史中尉，正色糾彈，無所回避，遠近肅然。",
          "translations": [
            {
              "lang": "en",
              "literal": "",
              "idiomatic": "",
              "translator": ""
            }
          ]
        },
        {
          "id": "s0013",
          "zh": "尋亂高祖後庭，高祖責罰之，因杖而斃，時年二十三。",
          "translations": [
            {
              "lang": "en",
              "literal": "",
              "idiomatic": "",
              "translator": ""
            }
          ]
        },
        {
          "id": "s0014",
          "zh": "贈使持節、侍中、都督冀定滄瀛幽殷幷肆雲朔十州諸軍事、驃騎大將軍、冀州刺史、太尉、尚書令，諡曰貞平。",
          "translations": [
            {
              "lang": "en",
              "literal": "",
              "idiomatic": "",
              "translator": ""
            }
          ]
        },
        {
          "id": "s0015",
          "zh": "天統三年，又贈假黃鉞、左丞相、太師、錄尚書事、冀州刺史，進爵為王，配饗高祖廟庭。",
          "translations": [
            {
              "lang": "en",
              "literal": "",
              "idiomatic": "",
              "translator": ""
            }
          ]
        },
        {
          "id": "s0016",
          "zh": "子叡嗣。",
          "translations": [
            {
              "lang": "en",
              "literal": "",
              "idiomatic": "",
              "translator": ""
            }
          ]
        }
      ],
      "translations": [
        {
          "lang": "en",
          "literal": "",
          "idiomatic": "",
          "translator": ""
        }
      ]
    },
    {
      "type": "paragraph",
      "sentences": [
        {
          "id": "s0017",
          "zh": "叡小名須拔，生三旬而孤，聰慧夙成，特為高祖所愛，養於宮中，令遊娘母之，恩同諸子。",
          "translations": [
            {
              "lang": "en",
              "literal": "",
              "idiomatic": "",
              "translator": ""
            }
          ]
        },
        {
          "id": "s0018",
          "zh": "魏興和中，襲爵南趙郡公。",
          "translations": [
            {
              "lang": "en",
              "literal": "",
              "idiomatic": "",
              "translator": ""
            }
          ]
        },
        {
          "id": "s0019",
          "zh": "至四歲，未嘗識母，其母則魏華陽公主也。",
          "translations": [
            {
              "lang": "en",
              "literal": "",
              "idiomatic": "",
              "translator": ""
            }
          ]
        },
        {
          "id": "s0020",
          "zh": "有鄭氏者，叡母之從母姊妹之女，戲語叡曰：「汝是我姨兒，何因倒親遊氏。",
          "translations": [
            {
              "lang": "en",
              "literal": "",
              "idiomatic": "",
              "translator": ""
            }
          ]
        },
        {
          "id": "s0021",
          "zh": "」叡因問訪，遂精神不怡。",
          "translations": [
            {
              "lang": "en",
              "literal": "",
              "idiomatic": "",
              "translator": ""
            }
          ]
        },
        {
          "id": "s0022",
          "zh": "高祖甚以為怪，疑其感疾，欲命醫看之。",
          "translations": [
            {
              "lang": "en",
              "literal": "",
              "idiomatic": "",
              "translator": ""
            }
          ]
        },
        {
          "id": "s0023",
          "zh": "叡對曰：「兒無患苦，但聞有所生，欲得暫見。",
          "translations": [
            {
              "lang": "en",
              "literal": "",
              "idiomatic": "",
              "translator": ""
            }
          ]
        },
        {
          "id": "s0024",
          "zh": "」高祖驚曰：「誰向汝道耶？",
          "translations": [
            {
              "lang": "en",
              "literal": "",
              "idiomatic": "",
              "translator": ""
            }
          ]
        },
        {
          "id": "s0025",
          "zh": "」叡具陳本末。",
          "translations": [
            {
              "lang": "en",
              "literal": "",
              "idiomatic": "",
              "translator": ""
            }
          ]
        },
        {
          "id": "s0026",
          "zh": "高祖命元夫人令就宮與叡相見，叡前跪拜，因抱頭大哭。",
          "translations": [
            {
              "lang": "en",
              "literal": "",
              "idiomatic": "",
              "translator": ""
            }
          ]
        },
        {
          "id": "s0027",
          "zh": "高祖甚以悲傷。",
          "translations": [
            {
              "lang": "en",
              "literal": "",
              "idiomatic": "",
              "translator": ""
            }
          ]
        },
        {
          "id": "s0028",
          "zh": "語平秦王曰：「此兒天生至孝，我兒子無有及者。",
          "translations": [
            {
              "lang": "en",
              "literal": "",
              "idiomatic": "",
              "translator": ""
            }
          ]
        },
        {
          "id": "s0029",
          "zh": "」遂為休務一日。",
          "translations": [
            {
              "lang": "en",
              "literal": "",
              "idiomatic": "",
              "translator": ""
            }
          ]
        },
        {
          "id": "s0030",
          "zh": "叡初讀《孝經》，至「資於事父」，輒流涕歔欷。",
          "translations": [
            {
              "lang": "en",
              "literal": "",
              "idiomatic": "",
              "translator": ""
            }
          ]
        },
        {
          "id": "s0031",
          "zh": "十歲喪母，高祖親送叡至領軍府，為叡發喪，與聲殞絕，哀感左右，三日水漿不入口。",
          "translations": [
            {
              "lang": "en",
              "literal": "",
              "idiomatic": "",
              "translator": ""
            }
          ]
        },
        {
          "id": "s0032",
          "zh": "高祖與武明婁皇后殷勤敦譬，方漸順旨。",
          "translations": [
            {
              "lang": "en",
              "literal": "",
              "idiomatic": "",
              "translator": ""
            }
          ]
        },
        {
          "id": "s0033",
          "zh": "居喪盡禮，持佛像長齋，至于骨立，杖而後起。",
          "translations": [
            {
              "lang": "en",
              "literal": "",
              "idiomatic": "",
              "translator": ""
            }
          ]
        },
        {
          "id": "s0034",
          "zh": "高祖令常山王共臥起，日夜說喻之。",
          "translations": [
            {
              "lang": "en",
              "literal": "",
              "idiomatic": "",
              "translator": ""
            }
          ]
        },
        {
          "id": "s0035",
          "zh": "並敕左右不聽進水，雖絕清漱，午後輒不肯食。",
          "translations": [
            {
              "lang": "en",
              "literal": "",
              "idiomatic": "",
              "translator": ""
            }
          ]
        },
        {
          "id": "s0036",
          "zh": "由是高祖食必喚叡同案。",
          "translations": [
            {
              "lang": "en",
              "literal": "",
              "idiomatic": "",
              "translator": ""
            }
          ]
        },
        {
          "id": "s0037",
          "zh": "其見湣惜如此。",
          "translations": [
            {
              "lang": "en",
              "literal": "",
              "idiomatic": "",
              "translator": ""
            }
          ]
        },
        {
          "id": "s0038",
          "zh": "高祖崩，哭泣嘔血。",
          "translations": [
            {
              "lang": "en",
              "literal": "",
              "idiomatic": "",
              "translator": ""
            }
          ]
        },
        {
          "id": "s0039",
          "zh": "及壯，將為婚娶，而貌有戚容。",
          "translations": [
            {
              "lang": "en",
              "literal": "",
              "idiomatic": "",
              "translator": ""
            }
          ]
        },
        {
          "id": "s0040",
          "zh": "世宗謂之曰：「我為爾娶鄭述祖女，門閥甚高，汝何所嫌而精神不樂？",
          "translations": [
            {
              "lang": "en",
              "literal": "",
              "idiomatic": "",
              "translator": ""
            }
          ]
        },
        {
          "id": "s0041",
          "zh": "」叡對曰：「自痛孤遺，常深膝下之慕，方從婚冠，彌用感切。",
          "translations": [
            {
              "lang": "en",
              "literal": "",
              "idiomatic": "",
              "translator": ""
            }
          ]
        },
        {
          "id": "s0042",
          "zh": "」言未卒，嗚咽不自勝。",
          "translations": [
            {
              "lang": "en",
              "literal": "",
              "idiomatic": "",
              "translator": ""
            }
          ]
        },
        {
          "id": "s0043",
          "zh": "世宗為之憫默。",
          "translations": [
            {
              "lang": "en",
              "literal": "",
              "idiomatic": "",
              "translator": ""
            }
          ]
        },
        {
          "id": "s0044",
          "zh": "勵己勤學，常夜久方罷。",
          "translations": [
            {
              "lang": "en",
              "literal": "",
              "idiomatic": "",
              "translator": ""
            }
          ]
        },
        {
          "id": "s0045",
          "zh": "武定末，除太子庶子。",
          "translations": [
            {
              "lang": "en",
              "literal": "",
              "idiomatic": "",
              "translator": ""
            }
          ]
        },
        {
          "id": "s0046",
          "zh": "顯祖受禪，進封爵為趙郡王，邑一千二百戶，遷散騎常侍。",
          "translations": [
            {
              "lang": "en",
              "literal": "",
              "idiomatic": "",
              "translator": ""
            }
          ]
        }
      ],
      "translations": [
        {
          "lang": "en",
          "literal": "",
          "idiomatic": "",
          "translator": ""
        }
      ]
    },
    {
      "type": "paragraph",
      "sentences": [
        {
          "id": "s0047",
          "zh": "叡身長七尺，容儀甚偉，閑習吏職，有知人之鑒。",
          "translations": [
            {
              "lang": "en",
              "literal": "",
              "idiomatic": "",
              "translator": ""
            }
          ]
        },
        {
          "id": "s0048",
          "zh": "二年，出為定州刺史，加撫軍將軍、六州大都督，時年十七。",
          "translations": [
            {
              "lang": "en",
              "literal": "",
              "idiomatic": "",
              "translator": ""
            }
          ]
        },
        {
          "id": "s0049",
          "zh": "叡留心庶事，糾摘姦非，勸課農桑，接禮民儁，所部大治，稱為良牧。",
          "translations": [
            {
              "lang": "en",
              "literal": "",
              "idiomatic": "",
              "translator": ""
            }
          ]
        },
        {
          "id": "s0050",
          "zh": "三年，加儀同三司。",
          "translations": [
            {
              "lang": "en",
              "literal": "",
              "idiomatic": "",
              "translator": ""
            }
          ]
        },
        {
          "id": "s0051",
          "zh": "六年，詔叡領山東兵數萬監築長城。",
          "translations": [
            {
              "lang": "en",
              "literal": "",
              "idiomatic": "",
              "translator": ""
            }
          ]
        },
        {
          "id": "s0052",
          "zh": "于時盛夏六月，叡在途中，屏除蓋扇，親與軍人同其勞苦。",
          "translations": [
            {
              "lang": "en",
              "literal": "",
              "idiomatic": "",
              "translator": ""
            }
          ]
        },
        {
          "id": "s0053",
          "zh": "而定州先有冰室，每歲藏冰，長史宋欽道以叡冒犯暑熱，遂遣輿冰，倍道追送。",
          "translations": [
            {
              "lang": "en",
              "literal": "",
              "idiomatic": "",
              "translator": ""
            }
          ]
        },
        {
          "id": "s0054",
          "zh": "正值日中停車，炎赫尤甚，人皆不堪，而送冰者至，咸謂得冰一時之要。",
          "translations": [
            {
              "lang": "en",
              "literal": "",
              "idiomatic": "",
              "translator": ""
            }
          ]
        },
        {
          "id": "s0055",
          "zh": "叡乃對之嘆息云 ：「三軍之人，皆飲溫水，吾以何義，獨進寒冰，非追名古將，實情所不忍。",
          "translations": [
            {
              "lang": "en",
              "literal": "",
              "idiomatic": "",
              "translator": ""
            }
          ]
        },
        {
          "id": "s0056",
          "zh": "」遂至消液，竟不一嘗。",
          "translations": [
            {
              "lang": "en",
              "literal": "",
              "idiomatic": "",
              "translator": ""
            }
          ]
        },
        {
          "id": "s0057",
          "zh": "兵人感悅，遐邇稱嘆。",
          "translations": [
            {
              "lang": "en",
              "literal": "",
              "idiomatic": "",
              "translator": ""
            }
          ]
        },
        {
          "id": "s0058",
          "zh": "先是，役徒罷作，任其自返。",
          "translations": [
            {
              "lang": "en",
              "literal": "",
              "idiomatic": "",
              "translator": ""
            }
          ]
        },
        {
          "id": "s0059",
          "zh": "丁壯之輩，各自先歸；",
          "translations": [
            {
              "lang": "en",
              "literal": "",
              "idiomatic": "",
              "translator": ""
            }
          ]
        },
        {
          "id": "s0060",
          "zh": "羸弱之徒，棄在山北，加以饑病，多致僵殞。",
          "translations": [
            {
              "lang": "en",
              "literal": "",
              "idiomatic": "",
              "translator": ""
            }
          ]
        },
        {
          "id": "s0061",
          "zh": "叡於是親帥所部，與之俱還，配合州鄉，部分營伍，督帥監領，強弱相持，遇善水草，即為停頓，分有餘，贍不足，屯以全者十三四焉。",
          "translations": [
            {
              "lang": "en",
              "literal": "",
              "idiomatic": "",
              "translator": ""
            }
          ]
        }
      ],
      "translations": [
        {
          "lang": "en",
          "literal": "",
          "idiomatic": "",
          "translator": ""
        }
      ]
    },
    {
      "type": "paragraph",
      "sentences": [
        {
          "id": "s0062",
          "zh": "七年，詔以本官都督滄、瀛、幽、安、平、東燕六州諸軍事、滄州刺史。",
          "translations": [
            {
              "lang": "en",
              "literal": "",
              "idiomatic": "",
              "translator": ""
            }
          ]
        },
        {
          "id": "s0063",
          "zh": "八年，徵叡赴鄴，仍除北朔州刺史，都督北燕、北蔚、北恒三州，及庫推以西黃河以東長城諸鎮諸軍事。",
          "translations": [
            {
              "lang": "en",
              "literal": "",
              "idiomatic": "",
              "translator": ""
            }
          ]
        },
        {
          "id": "s0064",
          "zh": "叡慰撫新遷，量置烽戍，內防外禦，備有條法，大為兵民所安。",
          "translations": [
            {
              "lang": "en",
              "literal": "",
              "idiomatic": "",
              "translator": ""
            }
          ]
        },
        {
          "id": "s0065",
          "zh": "有無水之處，禱而掘井，鍬鍤裁下，泉源湧出，至今號曰趙郡王泉。",
          "translations": [
            {
              "lang": "en",
              "literal": "",
              "idiomatic": "",
              "translator": ""
            }
          ]
        }
      ],
      "translations": [
        {
          "lang": "en",
          "literal": "",
          "idiomatic": "",
          "translator": ""
        }
      ]
    },
    {
      "type": "paragraph",
      "sentences": [
        {
          "id": "s0066",
          "zh": "九年，車駕幸樓煩，叡朝於行宮，仍從還晉陽。",
          "translations": [
            {
              "lang": "en",
              "literal": "",
              "idiomatic": "",
              "translator": ""
            }
          ]
        },
        {
          "id": "s0067",
          "zh": "時濟南以太子監國，因立大都督府，與尚書省分理衆事，仍開府置佐。",
          "translations": [
            {
              "lang": "en",
              "literal": "",
              "idiomatic": "",
              "translator": ""
            }
          ]
        },
        {
          "id": "s0068",
          "zh": "顯祖特崇其選，乃除叡侍中、攝大都督府長史。",
          "translations": [
            {
              "lang": "en",
              "literal": "",
              "idiomatic": "",
              "translator": ""
            }
          ]
        },
        {
          "id": "s0069",
          "zh": "叡後因侍宴，顯祖從容顧謂常山王演等曰：「由來亦有如此長史不？",
          "translations": [
            {
              "lang": "en",
              "literal": "",
              "idiomatic": "",
              "translator": ""
            }
          ]
        },
        {
          "id": "s0070",
          "zh": "吾用此長史何如？",
          "translations": [
            {
              "lang": "en",
              "literal": "",
              "idiomatic": "",
              "translator": ""
            }
          ]
        },
        {
          "id": "s0071",
          "zh": "」演對曰：「陛下垂心庶政，優賢禮物，須拔進居蟬珥之榮，退當委要之職，自昔以來，實未聞如此銓授。",
          "translations": [
            {
              "lang": "en",
              "literal": "",
              "idiomatic": "",
              "translator": ""
            }
          ]
        },
        {
          "id": "s0072",
          "zh": "」帝曰：「吾於此亦自謂得宜。",
          "translations": [
            {
              "lang": "en",
              "literal": "",
              "idiomatic": "",
              "translator": ""
            }
          ]
        },
        {
          "id": "s0073",
          "zh": "」十年，轉儀同三司、侍中、將軍、長史，王如故。",
          "translations": [
            {
              "lang": "en",
              "literal": "",
              "idiomatic": "",
              "translator": ""
            }
          ]
        },
        {
          "id": "s0074",
          "zh": "尋加開府儀同三司、驃騎大將軍、太子太保。",
          "translations": [
            {
              "lang": "en",
              "literal": "",
              "idiomatic": "",
              "translator": ""
            }
          ]
        }
      ],
      "translations": [
        {
          "lang": "en",
          "literal": "",
          "idiomatic": "",
          "translator": ""
        }
      ]
    },
    {
      "type": "paragraph",
      "sentences": [
        {
          "id": "s0075",
          "zh": "皇建初，行幷州事。",
          "translations": [
            {
              "lang": "en",
              "literal": "",
              "idiomatic": "",
              "translator": ""
            }
          ]
        },
        {
          "id": "s0076",
          "zh": "孝昭臨崩，預受顧托，奉迎世祖於鄴，以功拜尚書令，別封浮陽郡公，監太史，太子太傅，議律令。",
          "translations": [
            {
              "lang": "en",
              "literal": "",
              "idiomatic": "",
              "translator": ""
            }
          ]
        },
        {
          "id": "s0077",
          "zh": "又以討北狄之功，封潁川郡公。",
          "translations": [
            {
              "lang": "en",
              "literal": "",
              "idiomatic": "",
              "translator": ""
            }
          ]
        },
        {
          "id": "s0078",
          "zh": "復拜尚書令，攝大宗正卿。",
          "translations": [
            {
              "lang": "en",
              "literal": "",
              "idiomatic": "",
              "translator": ""
            }
          ]
        },
        {
          "id": "s0079",
          "zh": "天統中，追贈叡父琛假黃鉞，母元氏贈趙郡王妃，諡曰貞昭，華陽長公主如故，有司備禮儀就墓拜授。",
          "translations": [
            {
              "lang": "en",
              "literal": "",
              "idiomatic": "",
              "translator": ""
            }
          ]
        },
        {
          "id": "s0080",
          "zh": "時隆冬盛寒，叡跣步號哭，面皆破裂，嘔血數升。",
          "translations": [
            {
              "lang": "en",
              "literal": "",
              "idiomatic": "",
              "translator": ""
            }
          ]
        },
        {
          "id": "s0081",
          "zh": "及還，不堪參謝，帝親就第看問。",
          "translations": [
            {
              "lang": "en",
              "literal": "",
              "idiomatic": "",
              "translator": ""
            }
          ]
        },
        {
          "id": "s0082",
          "zh": "拜司空，攝錄尚書事。",
          "translations": [
            {
              "lang": "en",
              "literal": "",
              "idiomatic": "",
              "translator": ""
            }
          ]
        },
        {
          "id": "s0083",
          "zh": "突厥嘗侵軼至幷州，帝親禦戎，六軍進止皆令取叡節度。",
          "translations": [
            {
              "lang": "en",
              "literal": "",
              "idiomatic": "",
              "translator": ""
            }
          ]
        },
        {
          "id": "s0084",
          "zh": "以功復封宣城郡公。",
          "translations": [
            {
              "lang": "en",
              "literal": "",
              "idiomatic": "",
              "translator": ""
            }
          ]
        },
        {
          "id": "s0085",
          "zh": "攝宗正卿，進拜太尉，監議五禮。",
          "translations": [
            {
              "lang": "en",
              "literal": "",
              "idiomatic": "",
              "translator": ""
            }
          ]
        },
        {
          "id": "s0086",
          "zh": "叡久典朝政，清真自守，譽望日隆，漸被疏忌，乃撰古之忠臣義士，號曰《要言》，以致其意。",
          "translations": [
            {
              "lang": "en",
              "literal": "",
              "idiomatic": "",
              "translator": ""
            }
          ]
        }
      ],
      "translations": [
        {
          "lang": "en",
          "literal": "",
          "idiomatic": "",
          "translator": ""
        }
      ]
    },
    {
      "type": "paragraph",
      "sentences": [
        {
          "id": "s0087",
          "zh": "世祖崩，葬後數日，叡與馮翊王潤、安德王延宗及元文遙奏後主云 ：「和士開不宜仍居內任。",
          "translations": [
            {
              "lang": "en",
              "literal": "",
              "idiomatic": "",
              "translator": ""
            }
          ]
        },
        {
          "id": "s0088",
          "zh": "」並入奏太后，因出士開為兗州刺史。",
          "translations": [
            {
              "lang": "en",
              "literal": "",
              "idiomatic": "",
              "translator": ""
            }
          ]
        },
        {
          "id": "s0089",
          "zh": "太后曰：「士開舊經驅使，欲留過百日。",
          "translations": [
            {
              "lang": "en",
              "literal": "",
              "idiomatic": "",
              "translator": ""
            }
          ]
        },
        {
          "id": "s0090",
          "zh": "」叡正色不許。",
          "translations": [
            {
              "lang": "en",
              "literal": "",
              "idiomatic": "",
              "translator": ""
            }
          ]
        },
        {
          "id": "s0091",
          "zh": "數日之內，太后數以為言。",
          "translations": [
            {
              "lang": "en",
              "literal": "",
              "idiomatic": "",
              "translator": ""
            }
          ]
        },
        {
          "id": "s0092",
          "zh": "有中官要人知太后密旨，謂叡曰：「太后意既如此，殿下何宜苦違。",
          "translations": [
            {
              "lang": "en",
              "literal": "",
              "idiomatic": "",
              "translator": ""
            }
          ]
        },
        {
          "id": "s0093",
          "zh": "」叡曰：「吾國家事重，死且不避，若貪生茍全，令國家擾攘，非吾志也。",
          "translations": [
            {
              "lang": "en",
              "literal": "",
              "idiomatic": "",
              "translator": ""
            }
          ]
        },
        {
          "id": "s0094",
          "zh": "況受先皇遺旨，委寄不輕。",
          "translations": [
            {
              "lang": "en",
              "literal": "",
              "idiomatic": "",
              "translator": ""
            }
          ]
        },
        {
          "id": "s0095",
          "zh": "今嗣主幼沖，豈可使邪臣在側。",
          "translations": [
            {
              "lang": "en",
              "literal": "",
              "idiomatic": "",
              "translator": ""
            }
          ]
        },
        {
          "id": "s0096",
          "zh": "不守之以正，何面戴天。",
          "translations": [
            {
              "lang": "en",
              "literal": "",
              "idiomatic": "",
              "translator": ""
            }
          ]
        },
        {
          "id": "s0097",
          "zh": "」遂重進言，詞理懇切。",
          "translations": [
            {
              "lang": "en",
              "literal": "",
              "idiomatic": "",
              "translator": ""
            }
          ]
        },
        {
          "id": "s0098",
          "zh": "太后令酌酒賜叡。",
          "translations": [
            {
              "lang": "en",
              "literal": "",
              "idiomatic": "",
              "translator": ""
            }
          ]
        },
        {
          "id": "s0099",
          "zh": "叡正色曰：「今論國家大事，非為卮酒！",
          "translations": [
            {
              "lang": "en",
              "literal": "",
              "idiomatic": "",
              "translator": ""
            }
          ]
        },
        {
          "id": "s0100",
          "zh": "」言訖便出。",
          "translations": [
            {
              "lang": "en",
              "literal": "",
              "idiomatic": "",
              "translator": ""
            }
          ]
        },
        {
          "id": "s0101",
          "zh": "其夜，叡方寢，見一人可長丈五，臂長丈餘，當門向床，以臂壓叡，良久，遂失所在。",
          "translations": [
            {
              "lang": "en",
              "literal": "",
              "idiomatic": "",
              "translator": ""
            }
          ]
        },
        {
          "id": "s0102",
          "zh": "叡意甚惡之，便起坐獨嘆曰：「大丈夫命運一朝至此！",
          "translations": [
            {
              "lang": "en",
              "literal": "",
              "idiomatic": "",
              "translator": ""
            }
          ]
        },
        {
          "id": "s0103",
          "zh": "」恐為太后所殺，旦欲入朝，妻子咸諫止之。",
          "translations": [
            {
              "lang": "en",
              "literal": "",
              "idiomatic": "",
              "translator": ""
            }
          ]
        },
        {
          "id": "s0104",
          "zh": "叡曰：「自古忠臣，皆不顧身命，社稷事重，吾當以死效之，豈容令一婦人傾危宗廟。",
          "translations": [
            {
              "lang": "en",
              "literal": "",
              "idiomatic": "",
              "translator": ""
            }
          ]
        },
        {
          "id": "s0105",
          "zh": "且和士開何物豎子，如此縱橫，吾寧死事先皇，不忍見朝廷顛沛。",
          "translations": [
            {
              "lang": "en",
              "literal": "",
              "idiomatic": "",
              "translator": ""
            }
          ]
        },
        {
          "id": "s0106",
          "zh": "」至殿門，又有人曰：「願殿下勿入，慮有危變。",
          "translations": [
            {
              "lang": "en",
              "literal": "",
              "idiomatic": "",
              "translator": ""
            }
          ]
        },
        {
          "id": "s0107",
          "zh": "」叡曰：「吾上不負天，死亦無恨。",
          "translations": [
            {
              "lang": "en",
              "literal": "",
              "idiomatic": "",
              "translator": ""
            }
          ]
        },
        {
          "id": "s0108",
          "zh": "」入見太后，太后復以為言，叡執之彌固。",
          "translations": [
            {
              "lang": "en",
              "literal": "",
              "idiomatic": "",
              "translator": ""
            }
          ]
        },
        {
          "id": "s0109",
          "zh": "出至永巷，遇兵被執，送華林園，於雀離佛院令劉桃枝拉而殺之，時年三十六。",
          "translations": [
            {
              "lang": "en",
              "literal": "",
              "idiomatic": "",
              "translator": ""
            }
          ]
        },
        {
          "id": "s0110",
          "zh": "大霧三日，朝野冤惜之。",
          "translations": [
            {
              "lang": "en",
              "literal": "",
              "idiomatic": "",
              "translator": ""
            }
          ]
        },
        {
          "id": "s0111",
          "zh": "期年後，詔聽以王禮葬，竟無贈諡焉。",
          "translations": [
            {
              "lang": "en",
              "literal": "",
              "idiomatic": "",
              "translator": ""
            }
          ]
        }
      ],
      "translations": [
        {
          "lang": "en",
          "literal": "",
          "idiomatic": "",
          "translator": ""
        }
      ]
    },
    {
      "type": "paragraph",
      "sentences": [
        {
          "id": "s0112",
          "zh": "子整信嗣。",
          "translations": [
            {
              "lang": "en",
              "literal": "",
              "idiomatic": "",
              "translator": ""
            }
          ]
        },
        {
          "id": "s0113",
          "zh": "歷散騎常侍、儀同三司。",
          "translations": [
            {
              "lang": "en",
              "literal": "",
              "idiomatic": "",
              "translator": ""
            }
          ]
        },
        {
          "id": "s0114",
          "zh": "好學有行檢，少年時因獵墜馬，傷腰腳，卒不能行起，終於長安。",
          "translations": [
            {
              "lang": "en",
              "literal": "",
              "idiomatic": "",
              "translator": ""
            }
          ]
        },
        {
          "id": "s0115",
          "zh": "琛同母弟惠寶早亡，元象初，贈侍中、尚書令、都督四州諸軍事、青州刺史。",
          "translations": [
            {
              "lang": "en",
              "literal": "",
              "idiomatic": "",
              "translator": ""
            }
          ]
        },
        {
          "id": "s0116",
          "zh": "天統三年，重贈十州都督，封陳留王，諡曰文恭，以清河王岳第十子敬文嗣。",
          "translations": [
            {
              "lang": "en",
              "literal": "",
              "idiomatic": "",
              "translator": ""
            }
          ]
        }
      ],
      "translations": [
        {
          "lang": "en",
          "literal": "",
          "idiomatic": "",
          "translator": ""
        }
      ]
    },
    {
      "type": "paragraph",
      "sentences": [
        {
          "id": "s0117",
          "zh": "清河王岳，字洪略，高祖從父弟也。",
          "translations": [
            {
              "lang": "en",
              "literal": "",
              "idiomatic": "",
              "translator": ""
            }
          ]
        },
        {
          "id": "s0118",
          "zh": "父翻，字飛雀，魏朝贈太尉，諡孝宣公。",
          "translations": [
            {
              "lang": "en",
              "literal": "",
              "idiomatic": "",
              "translator": ""
            }
          ]
        },
        {
          "id": "s0119",
          "zh": "岳幼時孤貧，人未之知也，長而敦直，姿貌嶷然，沈深有器量。",
          "translations": [
            {
              "lang": "en",
              "literal": "",
              "idiomatic": "",
              "translator": ""
            }
          ]
        },
        {
          "id": "s0120",
          "zh": "初，岳家於洛邑，高祖每奉使入洛，必止于岳舍。",
          "translations": [
            {
              "lang": "en",
              "literal": "",
              "idiomatic": "",
              "translator": ""
            }
          ]
        },
        {
          "id": "s0121",
          "zh": "岳母山氏，嘗夜起，見高祖室中有光，密往覘之，乃無燈，即移高祖於別室，如前所見。",
          "translations": [
            {
              "lang": "en",
              "literal": "",
              "idiomatic": "",
              "translator": ""
            }
          ]
        },
        {
          "id": "s0122",
          "zh": "怪其神異，詣卜者筮之，遇《幹》之《大有》，占之曰：「吉，《易》稱『飛龍在天，大人造也』，飛龍九五大人之卦，貴不可言。",
          "translations": [
            {
              "lang": "en",
              "literal": "",
              "idiomatic": "",
              "translator": ""
            }
          ]
        },
        {
          "id": "s0123",
          "zh": "」山氏歸報高祖。",
          "translations": [
            {
              "lang": "en",
              "literal": "",
              "idiomatic": "",
              "translator": ""
            }
          ]
        },
        {
          "id": "s0124",
          "zh": "後高祖起兵於信都，山氏聞之，大喜，謂岳曰：「赤光之瑞，今當驗矣，汝可間行從之，共圖大計。",
          "translations": [
            {
              "lang": "en",
              "literal": "",
              "idiomatic": "",
              "translator": ""
            }
          ]
        },
        {
          "id": "s0125",
          "zh": "」岳遂往信都。",
          "translations": [
            {
              "lang": "en",
              "literal": "",
              "idiomatic": "",
              "translator": ""
            }
          ]
        },
        {
          "id": "s0126",
          "zh": "高祖見之，大悅。",
          "translations": [
            {
              "lang": "en",
              "literal": "",
              "idiomatic": "",
              "translator": ""
            }
          ]
        }
      ],
      "translations": [
        {
          "lang": "en",
          "literal": "",
          "idiomatic": "",
          "translator": ""
        }
      ]
    },
    {
      "type": "paragraph",
      "sentences": [
        {
          "id": "s0127",
          "zh": "中興初，除散騎常侍、鎮東將軍、金紫光祿大夫，領武衛將軍。",
          "translations": [
            {
              "lang": "en",
              "literal": "",
              "idiomatic": "",
              "translator": ""
            }
          ]
        },
        {
          "id": "s0128",
          "zh": "高祖與四胡戰于韓陵，高祖將中軍，高昂將左軍，岳將右軍。",
          "translations": [
            {
              "lang": "en",
              "literal": "",
              "idiomatic": "",
              "translator": ""
            }
          ]
        },
        {
          "id": "s0129",
          "zh": "中軍敗績，賊乘之，岳舉麾大呼，橫沖賊陣，高祖方得回師，表裏奮擊，因大破賊。",
          "translations": [
            {
              "lang": "en",
              "literal": "",
              "idiomatic": "",
              "translator": ""
            }
          ]
        },
        {
          "id": "s0130",
          "zh": "以功除衛將軍、右光祿大夫，仍領武衛。",
          "translations": [
            {
              "lang": "en",
              "literal": "",
              "idiomatic": "",
              "translator": ""
            }
          ]
        },
        {
          "id": "s0131",
          "zh": "太昌初，除車騎將軍、左光祿大夫，領左右衛，封清河郡公，食邑二千戶。",
          "translations": [
            {
              "lang": "en",
              "literal": "",
              "idiomatic": "",
              "translator": ""
            }
          ]
        },
        {
          "id": "s0132",
          "zh": "母山氏，封為郡君，授女侍中，入侍皇后。",
          "translations": [
            {
              "lang": "en",
              "literal": "",
              "idiomatic": "",
              "translator": ""
            }
          ]
        },
        {
          "id": "s0133",
          "zh": "時尒朱兆猶據幷州，高祖將討之，令岳留鎮京師，遷驃騎大將軍、儀同三司。",
          "translations": [
            {
              "lang": "en",
              "literal": "",
              "idiomatic": "",
              "translator": ""
            }
          ]
        },
        {
          "id": "s0134",
          "zh": "天平二年，除侍中、六州軍事都督，尋加開府。",
          "translations": [
            {
              "lang": "en",
              "literal": "",
              "idiomatic": "",
              "translator": ""
            }
          ]
        },
        {
          "id": "s0135",
          "zh": "岳辟引時賢，以為僚屬，論者以為美。",
          "translations": [
            {
              "lang": "en",
              "literal": "",
              "idiomatic": "",
              "translator": ""
            }
          ]
        },
        {
          "id": "s0136",
          "zh": "尋都監典書，復為侍學，除使持節、六州大都督、冀州大中正。",
          "translations": [
            {
              "lang": "en",
              "literal": "",
              "idiomatic": "",
              "translator": ""
            }
          ]
        },
        {
          "id": "s0137",
          "zh": "俄拜京畿大都督，其六州事悉詣京畿。",
          "translations": [
            {
              "lang": "en",
              "literal": "",
              "idiomatic": "",
              "translator": ""
            }
          ]
        },
        {
          "id": "s0138",
          "zh": "時高祖統務晉陽，岳與侍中孫騰等在京師輔政。",
          "translations": [
            {
              "lang": "en",
              "literal": "",
              "idiomatic": "",
              "translator": ""
            }
          ]
        },
        {
          "id": "s0139",
          "zh": "元象二年，遭母憂去職。",
          "translations": [
            {
              "lang": "en",
              "literal": "",
              "idiomatic": "",
              "translator": ""
            }
          ]
        },
        {
          "id": "s0140",
          "zh": "岳性至孝，盡力色養，母若有疾，衣不解帶，及遭喪，哀毀骨立，高祖深以憂之，每日遣人勞勉。",
          "translations": [
            {
              "lang": "en",
              "literal": "",
              "idiomatic": "",
              "translator": ""
            }
          ]
        },
        {
          "id": "s0141",
          "zh": "尋起復本任。",
          "translations": [
            {
              "lang": "en",
              "literal": "",
              "idiomatic": "",
              "translator": ""
            }
          ]
        },
        {
          "id": "s0142",
          "zh": "二年，除兼領軍將軍。",
          "translations": [
            {
              "lang": "en",
              "literal": "",
              "idiomatic": "",
              "translator": ""
            }
          ]
        },
        {
          "id": "s0143",
          "zh": "興和初，世宗入總朝政，岳出為使持節、都督、冀州刺史，侍中、驃騎、開府儀同如故。",
          "translations": [
            {
              "lang": "en",
              "literal": "",
              "idiomatic": "",
              "translator": ""
            }
          ]
        },
        {
          "id": "s0144",
          "zh": "三年，轉青州刺史。",
          "translations": [
            {
              "lang": "en",
              "literal": "",
              "idiomatic": "",
              "translator": ""
            }
          ]
        },
        {
          "id": "s0145",
          "zh": "岳任權日久，素為朝野畏服，及為二藩，百姓望風讋憚。",
          "translations": [
            {
              "lang": "en",
              "literal": "",
              "idiomatic": "",
              "translator": ""
            }
          ]
        },
        {
          "id": "s0146",
          "zh": "武定元年，除晉州刺史、西南道大都督，得綏邊之稱。",
          "translations": [
            {
              "lang": "en",
              "literal": "",
              "idiomatic": "",
              "translator": ""
            }
          ]
        },
        {
          "id": "s0147",
          "zh": "時岳遇患，高祖令還幷治療，疾瘳，復令赴職。",
          "translations": [
            {
              "lang": "en",
              "literal": "",
              "idiomatic": "",
              "translator": ""
            }
          ]
        }
      ],
      "translations": [
        {
          "lang": "en",
          "literal": "",
          "idiomatic": "",
          "translator": ""
        }
      ]
    },
    {
      "type": "paragraph",
      "sentences": [
        {
          "id": "s0148",
          "zh": "及高祖崩，侯景叛，世宗徵岳還幷，共圖取景之計。",
          "translations": [
            {
              "lang": "en",
              "literal": "",
              "idiomatic": "",
              "translator": ""
            }
          ]
        },
        {
          "id": "s0149",
          "zh": "而武帝乘間遣其貞陽侯明率衆於寒山，擁泗水灌彭城，與景為掎角聲援。",
          "translations": [
            {
              "lang": "en",
              "literal": "",
              "idiomatic": "",
              "translator": ""
            }
          ]
        },
        {
          "id": "s0150",
          "zh": "岳總帥諸軍南討，與行臺慕容紹宗等擊明，大破之，臨陣擒明及其大將胡貴孫，自餘俘馘數萬。",
          "translations": [
            {
              "lang": "en",
              "literal": "",
              "idiomatic": "",
              "translator": ""
            }
          ]
        },
        {
          "id": "s0151",
          "zh": "景乃擁衆於渦陽，與左衛將軍劉豐等相持。",
          "translations": [
            {
              "lang": "en",
              "literal": "",
              "idiomatic": "",
              "translator": ""
            }
          ]
        },
        {
          "id": "s0152",
          "zh": "岳回軍追討，又破之，景單騎逃竄。",
          "translations": [
            {
              "lang": "en",
              "literal": "",
              "idiomatic": "",
              "translator": ""
            }
          ]
        },
        {
          "id": "s0153",
          "zh": "六年，以功除侍中、太尉，餘如故，別封新昌縣子。",
          "translations": [
            {
              "lang": "en",
              "literal": "",
              "idiomatic": "",
              "translator": ""
            }
          ]
        },
        {
          "id": "s0154",
          "zh": "又拜使持節、河南總管、大都督，統慕容紹宗、劉豐等討王思政於長社。",
          "translations": [
            {
              "lang": "en",
              "literal": "",
              "idiomatic": "",
              "translator": ""
            }
          ]
        },
        {
          "id": "s0155",
          "zh": "思政嬰城自守，岳等引洧水灌城。",
          "translations": [
            {
              "lang": "en",
              "literal": "",
              "idiomatic": "",
              "translator": ""
            }
          ]
        },
        {
          "id": "s0156",
          "zh": "紹宗、劉豐為思政所獲，關西出兵援思政，岳內外防禦，甚有謀算。",
          "translations": [
            {
              "lang": "en",
              "literal": "",
              "idiomatic": "",
              "translator": ""
            }
          ]
        },
        {
          "id": "s0157",
          "zh": "城不沒者三板。",
          "translations": [
            {
              "lang": "en",
              "literal": "",
              "idiomatic": "",
              "translator": ""
            }
          ]
        },
        {
          "id": "s0158",
          "zh": "會世宗親臨，數日城下，獲思政等。",
          "translations": [
            {
              "lang": "en",
              "literal": "",
              "idiomatic": "",
              "translator": ""
            }
          ]
        },
        {
          "id": "s0159",
          "zh": "以功別封真定縣男，世宗以為己功，故賞典弗弘也。",
          "translations": [
            {
              "lang": "en",
              "literal": "",
              "idiomatic": "",
              "translator": ""
            }
          ]
        }
      ],
      "translations": [
        {
          "lang": "en",
          "literal": "",
          "idiomatic": "",
          "translator": ""
        }
      ]
    },
    {
      "type": "paragraph",
      "sentences": [
        {
          "id": "s0160",
          "zh": "世宗崩，顯祖出撫晉陽，令岳以本官兼尚書左僕射，留鎮京師。",
          "translations": [
            {
              "lang": "en",
              "literal": "",
              "idiomatic": "",
              "translator": ""
            }
          ]
        },
        {
          "id": "s0161",
          "zh": "天保初，進封清河郡王，尋除使持節、驃騎大將軍、開府儀同三司、宗師、司州牧。",
          "translations": [
            {
              "lang": "en",
              "literal": "",
              "idiomatic": "",
              "translator": ""
            }
          ]
        },
        {
          "id": "s0162",
          "zh": "五年，加太保。",
          "translations": [
            {
              "lang": "en",
              "literal": "",
              "idiomatic": "",
              "translator": ""
            }
          ]
        },
        {
          "id": "s0163",
          "zh": "梁蕭繹為周軍所逼，遣使告急，且請援。",
          "translations": [
            {
              "lang": "en",
              "literal": "",
              "idiomatic": "",
              "translator": ""
            }
          ]
        },
        {
          "id": "s0164",
          "zh": "冬，詔岳為西南道大行臺，統司徒潘相樂等救江陵。",
          "translations": [
            {
              "lang": "en",
              "literal": "",
              "idiomatic": "",
              "translator": ""
            }
          ]
        },
        {
          "id": "s0165",
          "zh": "六年正月，師次義陽，遇荊州陷，因略地南至郢州，獲梁州刺史司徒陸法和，仍剋郢州。",
          "translations": [
            {
              "lang": "en",
              "literal": "",
              "idiomatic": "",
              "translator": ""
            }
          ]
        },
        {
          "id": "s0166",
          "zh": "岳先送法和於京師，遣儀同慕容儼據郢城。",
          "translations": [
            {
              "lang": "en",
              "literal": "",
              "idiomatic": "",
              "translator": ""
            }
          ]
        },
        {
          "id": "s0167",
          "zh": "朝廷知江陵陷，詔岳旋師。",
          "translations": [
            {
              "lang": "en",
              "literal": "",
              "idiomatic": "",
              "translator": ""
            }
          ]
        }
      ],
      "translations": [
        {
          "lang": "en",
          "literal": "",
          "idiomatic": "",
          "translator": ""
        }
      ]
    },
    {
      "type": "paragraph",
      "sentences": [
        {
          "id": "s0168",
          "zh": "岳自討寒山、長社及出隨、陸，並有功績，威名彌重。",
          "translations": [
            {
              "lang": "en",
              "literal": "",
              "idiomatic": "",
              "translator": ""
            }
          ]
        },
        {
          "id": "s0169",
          "zh": "而性華侈，尤悅酒色，歌姬舞女，陳鼎擊鐘，諸王皆不及也。",
          "translations": [
            {
              "lang": "en",
              "literal": "",
              "idiomatic": "",
              "translator": ""
            }
          ]
        },
        {
          "id": "s0170",
          "zh": "初，高歸彥少孤，高祖令岳撫養，輕其年幼，情禮甚薄。",
          "translations": [
            {
              "lang": "en",
              "literal": "",
              "idiomatic": "",
              "translator": ""
            }
          ]
        },
        {
          "id": "s0171",
          "zh": "歸彥內銜之而未嘗出口。",
          "translations": [
            {
              "lang": "en",
              "literal": "",
              "idiomatic": "",
              "translator": ""
            }
          ]
        },
        {
          "id": "s0172",
          "zh": "及歸彥為領軍，大被寵遇，岳謂其德己，更倚賴之。",
          "translations": [
            {
              "lang": "en",
              "literal": "",
              "idiomatic": "",
              "translator": ""
            }
          ]
        },
        {
          "id": "s0173",
          "zh": "歸彥密構其短。",
          "translations": [
            {
              "lang": "en",
              "literal": "",
              "idiomatic": "",
              "translator": ""
            }
          ]
        },
        {
          "id": "s0174",
          "zh": "岳於城南起宅，聽事後開巷。",
          "translations": [
            {
              "lang": "en",
              "literal": "",
              "idiomatic": "",
              "translator": ""
            }
          ]
        },
        {
          "id": "s0175",
          "zh": "歸彥奏帝曰：「清河造宅，僭擬帝宮，制為永巷，但唯無闕耳。",
          "translations": [
            {
              "lang": "en",
              "literal": "",
              "idiomatic": "",
              "translator": ""
            }
          ]
        },
        {
          "id": "s0176",
          "zh": "」顯祖聞而惡之，漸以疏岳。",
          "translations": [
            {
              "lang": "en",
              "literal": "",
              "idiomatic": "",
              "translator": ""
            }
          ]
        },
        {
          "id": "s0177",
          "zh": "仍屬顯祖召鄴下婦人薛氏入宮，而岳先嘗喚之至宅，由其姊也。",
          "translations": [
            {
              "lang": "en",
              "literal": "",
              "idiomatic": "",
              "translator": ""
            }
          ]
        },
        {
          "id": "s0178",
          "zh": "帝懸薛氏姊而鋸殺之，讓岳以為姦民女。",
          "translations": [
            {
              "lang": "en",
              "literal": "",
              "idiomatic": "",
              "translator": ""
            }
          ]
        },
        {
          "id": "s0179",
          "zh": "岳曰：「臣本欲取之，嫌其輕薄不用，非姦也。",
          "translations": [
            {
              "lang": "en",
              "literal": "",
              "idiomatic": "",
              "translator": ""
            }
          ]
        },
        {
          "id": "s0180",
          "zh": "」帝益怒。",
          "translations": [
            {
              "lang": "en",
              "literal": "",
              "idiomatic": "",
              "translator": ""
            }
          ]
        },
        {
          "id": "s0181",
          "zh": "六年十一月，使高歸彥就宅切責之。",
          "translations": [
            {
              "lang": "en",
              "literal": "",
              "idiomatic": "",
              "translator": ""
            }
          ]
        },
        {
          "id": "s0182",
          "zh": "岳憂悸不知所為，數日而薨，故時論紛然，以為賜鴆也。",
          "translations": [
            {
              "lang": "en",
              "literal": "",
              "idiomatic": "",
              "translator": ""
            }
          ]
        },
        {
          "id": "s0183",
          "zh": "朝野嘆惜之。",
          "translations": [
            {
              "lang": "en",
              "literal": "",
              "idiomatic": "",
              "translator": ""
            }
          ]
        },
        {
          "id": "s0184",
          "zh": "時年四十四。",
          "translations": [
            {
              "lang": "en",
              "literal": "",
              "idiomatic": "",
              "translator": ""
            }
          ]
        },
        {
          "id": "s0185",
          "zh": "詔大鴻臚監護喪事，贈使持節、都督冀定滄瀛趙幽濟七州諸軍、太宰、太傅、定州刺史，假黃鉞，給轀輬車，赗物二千段，諡曰昭武。",
          "translations": [
            {
              "lang": "en",
              "literal": "",
              "idiomatic": "",
              "translator": ""
            }
          ]
        }
      ],
      "translations": [
        {
          "lang": "en",
          "literal": "",
          "idiomatic": "",
          "translator": ""
        }
      ]
    },
    {
      "type": "paragraph",
      "sentences": [
        {
          "id": "s0186",
          "zh": "初，岳與高祖經綸天下，家有私兵，並畜戎器，儲甲千餘領。",
          "translations": [
            {
              "lang": "en",
              "literal": "",
              "idiomatic": "",
              "translator": ""
            }
          ]
        },
        {
          "id": "s0187",
          "zh": "世宗之末，岳以四海無事，表求納之。",
          "translations": [
            {
              "lang": "en",
              "literal": "",
              "idiomatic": "",
              "translator": ""
            }
          ]
        },
        {
          "id": "s0188",
          "zh": "世宗敦至親之重，推心相任，云 ：「叔屬居肺腑，職在維城，所有之甲，本資國用，叔何疑而納之。",
          "translations": [
            {
              "lang": "en",
              "literal": "",
              "idiomatic": "",
              "translator": ""
            }
          ]
        },
        {
          "id": "s0189",
          "zh": "」文宣之世，亦頻請納，又固不許。",
          "translations": [
            {
              "lang": "en",
              "literal": "",
              "idiomatic": "",
              "translator": ""
            }
          ]
        },
        {
          "id": "s0190",
          "zh": "及將薨，遺表謝恩，並請上甲于武庫，至此葬畢，方許納焉。",
          "translations": [
            {
              "lang": "en",
              "literal": "",
              "idiomatic": "",
              "translator": ""
            }
          ]
        },
        {
          "id": "s0191",
          "zh": "皇建中，配享世宗廟庭。",
          "translations": [
            {
              "lang": "en",
              "literal": "",
              "idiomatic": "",
              "translator": ""
            }
          ]
        },
        {
          "id": "s0192",
          "zh": "後歸彥反，世祖知其前譖，曰：「清河忠烈，盡力皇家，而歸彥毀之，間吾骨肉。",
          "translations": [
            {
              "lang": "en",
              "literal": "",
              "idiomatic": "",
              "translator": ""
            }
          ]
        },
        {
          "id": "s0193",
          "zh": "」籍沒歸彥，以良賤百口賜岳家。",
          "translations": [
            {
              "lang": "en",
              "literal": "",
              "idiomatic": "",
              "translator": ""
            }
          ]
        },
        {
          "id": "s0194",
          "zh": "後又思岳之功，重贈太師、太保，餘如故。",
          "translations": [
            {
              "lang": "en",
              "literal": "",
              "idiomatic": "",
              "translator": ""
            }
          ]
        },
        {
          "id": "s0195",
          "zh": "子勱嗣。",
          "translations": [
            {
              "lang": "en",
              "literal": "",
              "idiomatic": "",
              "translator": ""
            }
          ]
        }
      ],
      "translations": [
        {
          "lang": "en",
          "literal": "",
          "idiomatic": "",
          "translator": ""
        }
      ]
    },
    {
      "type": "paragraph",
      "sentences": [
        {
          "id": "s0196",
          "zh": "勱，字敬德，夙智早成，為顯祖所愛。",
          "translations": [
            {
              "lang": "en",
              "literal": "",
              "idiomatic": "",
              "translator": ""
            }
          ]
        },
        {
          "id": "s0197",
          "zh": "年七歲，遣侍皇太子。",
          "translations": [
            {
              "lang": "en",
              "literal": "",
              "idiomatic": "",
              "translator": ""
            }
          ]
        },
        {
          "id": "s0198",
          "zh": "後除青州刺史，拜日，顯祖戒之曰：「叔父前牧青州，甚有遺惠，故遣汝慰彼黎庶，宜好用心，無墜聲績。",
          "translations": [
            {
              "lang": "en",
              "literal": "",
              "idiomatic": "",
              "translator": ""
            }
          ]
        },
        {
          "id": "s0199",
          "zh": "」勱流涕對曰：「臣以蒙幼，濫叨拔擢，雖竭庸短，懼忝先政。",
          "translations": [
            {
              "lang": "en",
              "literal": "",
              "idiomatic": "",
              "translator": ""
            }
          ]
        },
        {
          "id": "s0200",
          "zh": "」帝曰：「汝既能有此言，吾不慮也。",
          "translations": [
            {
              "lang": "en",
              "literal": "",
              "idiomatic": "",
              "translator": ""
            }
          ]
        },
        {
          "id": "s0201",
          "zh": "」尋追授武衛將軍、領軍、祠部尚書、開府儀同三司。",
          "translations": [
            {
              "lang": "en",
              "literal": "",
              "idiomatic": "",
              "translator": ""
            }
          ]
        },
        {
          "id": "s0202",
          "zh": "以清河地在畿內，改封樂安王。",
          "translations": [
            {
              "lang": "en",
              "literal": "",
              "idiomatic": "",
              "translator": ""
            }
          ]
        },
        {
          "id": "s0203",
          "zh": "轉侍中、尚書右僕射，出為朔州行臺僕射。",
          "translations": [
            {
              "lang": "en",
              "literal": "",
              "idiomatic": "",
              "translator": ""
            }
          ]
        }
      ],
      "translations": [
        {
          "lang": "en",
          "literal": "",
          "idiomatic": "",
          "translator": ""
        }
      ]
    },
    {
      "type": "paragraph",
      "sentences": [
        {
          "id": "s0204",
          "zh": "後主晉州敗，太后從土門道還京師，敕勱統領兵馬，侍衛太后。",
          "translations": [
            {
              "lang": "en",
              "literal": "",
              "idiomatic": "",
              "translator": ""
            }
          ]
        },
        {
          "id": "s0205",
          "zh": "時佞幸閽寺，猶行暴虐，民間雞豬，悉放鷹犬搏噬取之。",
          "translations": [
            {
              "lang": "en",
              "literal": "",
              "idiomatic": "",
              "translator": ""
            }
          ]
        },
        {
          "id": "s0206",
          "zh": "勱收儀同三司茍子溢徇軍，欲行大戮。",
          "translations": [
            {
              "lang": "en",
              "literal": "",
              "idiomatic": "",
              "translator": ""
            }
          ]
        },
        {
          "id": "s0207",
          "zh": "太后有令，然後釋之。",
          "translations": [
            {
              "lang": "en",
              "literal": "",
              "idiomatic": "",
              "translator": ""
            }
          ]
        },
        {
          "id": "s0208",
          "zh": "劉文殊竊謂勱曰：「子溢之徒，言成禍福，何容如此，豈不慮後生毀謗耶？",
          "translations": [
            {
              "lang": "en",
              "literal": "",
              "idiomatic": "",
              "translator": ""
            }
          ]
        },
        {
          "id": "s0209",
          "zh": "」勱攘袂語文殊曰：「自獻武皇帝以來，撫養士卒，委政親賢，用武行師，未有折衂。",
          "translations": [
            {
              "lang": "en",
              "literal": "",
              "idiomatic": "",
              "translator": ""
            }
          ]
        },
        {
          "id": "s0210",
          "zh": "今西寇已次幷州，達官多悉委叛，正坐此輩專政弄權，所以內外離心，衣冠解體。",
          "translations": [
            {
              "lang": "en",
              "literal": "",
              "idiomatic": "",
              "translator": ""
            }
          ]
        },
        {
          "id": "s0211",
          "zh": "若得今日斬此卒，明日及誅，亦無所恨。",
          "translations": [
            {
              "lang": "en",
              "literal": "",
              "idiomatic": "",
              "translator": ""
            }
          ]
        },
        {
          "id": "s0212",
          "zh": "王國家姻婭，須同疾惡，返為此言，豈所望乎！",
          "translations": [
            {
              "lang": "en",
              "literal": "",
              "idiomatic": "",
              "translator": ""
            }
          ]
        },
        {
          "id": "s0213",
          "zh": "」太后還至鄴，周軍續至，人皆恟懼，無有鬭心，朝士出降，晝夜相屬。",
          "translations": [
            {
              "lang": "en",
              "literal": "",
              "idiomatic": "",
              "translator": ""
            }
          ]
        },
        {
          "id": "s0214",
          "zh": "勱因奏後主曰：「今所翻叛，多是貴人，至於卒伍，猶未離貳。",
          "translations": [
            {
              "lang": "en",
              "literal": "",
              "idiomatic": "",
              "translator": ""
            }
          ]
        },
        {
          "id": "s0215",
          "zh": "請追五品已上家屬，置之三臺，因協之曰：『若戰不捷，即退焚臺。",
          "translations": [
            {
              "lang": "en",
              "literal": "",
              "idiomatic": "",
              "translator": ""
            }
          ]
        },
        {
          "id": "s0216",
          "zh": "』此曹顧惜妻子，必當死戰。",
          "translations": [
            {
              "lang": "en",
              "literal": "",
              "idiomatic": "",
              "translator": ""
            }
          ]
        },
        {
          "id": "s0217",
          "zh": "且王師頻北，賊徒輕我，今背城一決，理必破之，此亦計之上者。",
          "translations": [
            {
              "lang": "en",
              "literal": "",
              "idiomatic": "",
              "translator": ""
            }
          ]
        },
        {
          "id": "s0218",
          "zh": "」後主卒不能用。",
          "translations": [
            {
              "lang": "en",
              "literal": "",
              "idiomatic": "",
              "translator": ""
            }
          ]
        },
        {
          "id": "s0219",
          "zh": "齊亡入周，依例授開府。",
          "translations": [
            {
              "lang": "en",
              "literal": "",
              "idiomatic": "",
              "translator": ""
            }
          ]
        },
        {
          "id": "s0220",
          "zh": "隋朝歷楊、楚、光、洮四州刺史。",
          "translations": [
            {
              "lang": "en",
              "literal": "",
              "idiomatic": "",
              "translator": ""
            }
          ]
        },
        {
          "id": "s0221",
          "zh": "開皇中卒。",
          "translations": [
            {
              "lang": "en",
              "literal": "",
              "idiomatic": "",
              "translator": ""
            }
          ]
        }
      ],
      "translations": [
        {
          "lang": "en",
          "literal": "",
          "idiomatic": "",
          "translator": ""
        }
      ]
    },
    {
      "type": "paragraph",
      "sentences": [
        {
          "id": "s0222",
          "zh": "史臣曰：《易》稱：「天地盈虛，與時消息，況於人乎！",
          "translations": [
            {
              "lang": "en",
              "literal": "",
              "idiomatic": "",
              "translator": ""
            }
          ]
        },
        {
          "id": "s0223",
          "zh": "」蓋以通塞有期，汚隆適道。",
          "translations": [
            {
              "lang": "en",
              "literal": "",
              "idiomatic": "",
              "translator": ""
            }
          ]
        },
        {
          "id": "s0224",
          "zh": "舉世思治，則顯仁以應之；",
          "translations": [
            {
              "lang": "en",
              "literal": "",
              "idiomatic": "",
              "translator": ""
            }
          ]
        },
        {
          "id": "s0225",
          "zh": "小人道長，則儉德以避之。",
          "translations": [
            {
              "lang": "en",
              "literal": "",
              "idiomatic": "",
              "translator": ""
            }
          ]
        },
        {
          "id": "s0226",
          "zh": "至若負博陸之圖，處藩屏之地，而欲迷邦違難，其可得乎。",
          "translations": [
            {
              "lang": "en",
              "literal": "",
              "idiomatic": "",
              "translator": ""
            }
          ]
        },
        {
          "id": "s0227",
          "zh": "趙郡以跗萼之親，當顧命之重，高揖則宗社易危，去惡則人神俱泰。",
          "translations": [
            {
              "lang": "en",
              "literal": "",
              "idiomatic": "",
              "translator": ""
            }
          ]
        },
        {
          "id": "s0228",
          "zh": "是用安夫一德，同此貞心，踐畏途而不疑，履危機而莫懼。",
          "translations": [
            {
              "lang": "en",
              "literal": "",
              "idiomatic": "",
              "translator": ""
            }
          ]
        },
        {
          "id": "s0229",
          "zh": "以斯忠義，取斃尹凶慝。",
          "translations": [
            {
              "lang": "en",
              "literal": "",
              "idiomatic": "",
              "translator": ""
            }
          ]
        },
        {
          "id": "s0230",
          "zh": "豈道光四海，不遇周成之明；",
          "translations": [
            {
              "lang": "en",
              "literal": "",
              "idiomatic": "",
              "translator": ""
            }
          ]
        },
        {
          "id": "s0231",
          "zh": "將朝去三仁，終見殷墟之禍。",
          "translations": [
            {
              "lang": "en",
              "literal": "",
              "idiomatic": "",
              "translator": ""
            }
          ]
        },
        {
          "id": "s0232",
          "zh": "不然則邦國殄瘁，何影響之速乎！",
          "translations": [
            {
              "lang": "en",
              "literal": "",
              "idiomatic": "",
              "translator": ""
            }
          ]
        },
        {
          "id": "s0233",
          "zh": "清河屬經綸之會，自致青雲，出將入相，翊成鴻業，雖漢朝劉賈，魏室曹洪，俱未足論其高下。",
          "translations": [
            {
              "lang": "en",
              "literal": "",
              "idiomatic": "",
              "translator": ""
            }
          ]
        },
        {
          "id": "s0234",
          "zh": "天保不辰，易生悔咎，固不可掩其風烈，適以彰顯祖之失德云。",
          "translations": [
            {
              "lang": "en",
              "literal": "",
              "idiomatic": "",
              "translator": ""
            }
          ]
        }
      ],
      "translations": [
        {
          "lang": "en",
          "literal": "",
          "idiomatic": "",
          "translator": ""
        }
      ]
    },
    {
      "type": "paragraph",
      "sentences": [
        {
          "id": "s0235",
          "zh": "贊曰：趙郡英偉，風範凝正。",
          "translations": [
            {
              "lang": "en",
              "literal": "",
              "idiomatic": "",
              "translator": ""
            }
          ]
        },
        {
          "id": "s0236",
          "zh": "天道無親，斯人斯命。",
          "translations": [
            {
              "lang": "en",
              "literal": "",
              "idiomatic": "",
              "translator": ""
            }
          ]
        },
        {
          "id": "s0237",
          "zh": "赫赫清河，于以經國。",
          "translations": [
            {
              "lang": "en",
              "literal": "",
              "idiomatic": "",
              "translator": ""
            }
          ]
        },
        {
          "id": "s0238",
          "zh": "末路小疵，非為敗德。",
          "translations": [
            {
              "lang": "en",
              "literal": "",
              "idiomatic": "",
              "translator": ""
            }
          ]
        }
      ],
      "translations": [
        {
          "lang": "en",
          "literal": "",
          "idiomatic": "",
          "translator": ""
        }
      ]
    },
    {
      "type": "paragraph",
      "sentences": [
        {
          "id": "s0239",
          "zh": "全文以中華書局、一九七二年十一月、第一版《北齊書》為本校。",
          "translations": [
            {
              "lang": "en",
              "literal": "",
              "idiomatic": "",
              "translator": ""
            }
          ]
        }
      ],
      "translations": [
        {
          "lang": "en",
          "literal": "",
          "idiomatic": "",
          "translator": ""
        }
      ]
    }
  ]
}