{
  "meta": {
    "book": "qingshigao",
    "bookInfo": {
      "name": "Draft History of Qing",
      "chinese": "清史稿",
      "pinyin": "Qīngshǐgǎo",
      "dynasty": "Qing",
      "author": "Zhao Erxun et al.",
      "authorChinese": "趙爾巽等",
      "category": "otherWorks"
    },
    "chapter": "031",
    "url": "https://zh.wikisource.org/wiki/清史稿/卷31?action=raw",
    "wikisourceUrl": "https://zh.wikisource.org/wiki/清史稿/卷31?action=raw",
    "title": {
      "zh": "卷31 志六 天文六",
      "en": "",
      "raw": "卷31 志六 天文六"
    },
    "sentenceCount": 1,
    "translatedCount": 0,
    "glossarySize": 0,
    "scrapedAt": "2026-04-26T01:55:59.546Z",
    "translators": [],
    "citation": null
  },
  "content": [
    {
      "type": "paragraph",
      "sentences": [
        {
          "id": "s0001",
          "zh": "志六 天文六 （表略）",
          "translations": [
            {
              "lang": "en",
              "literal": "",
              "idiomatic": "",
              "translator": ""
            }
          ]
        }
      ],
      "translations": [
        {
          "lang": "en",
          "literal": "",
          "idiomatic": "",
          "translator": ""
        }
      ]
    }
  ]
}